<?xml version="1.0" encoding="utf-8"?>
<openerp>
    <data>

        <record model="ir.actions.act_window" id="action_shop">
            <field name="name">Shops</field>
            <field name="res_model">ecommerce.api.shop</field>
            <field name="view_type">form</field>
            <field name="view_mode">tree,form</field>
            <field name="view_id" />
        </record>

        <menuitem
            id="menu_root"
            name="Ecommerce API"
            sequence="500"
        />
        <menuitem
            id="menu_config"
            name="Config"
            parent="menu_root"
            sequence="10"
        />
        <menuitem
            id="menu_config_shop"
            name="Shops"
            parent="menu_config"
            sequence="10"
            action="action_shop"
        />

    </data>
</openerp>

